docs/commands/data_cleaning.md
docs/commands/local_cluster.md
docs/commands/pypi.md
docs/commands/webserver.md
fastchat/__init__.py
fastchat/constants.py
fastchat/conversation.py
fastchat/utils.py
fastchat/version.py
fastchat/client/__init__.py
fastchat/client/api.py
fastchat/client/test_client.py
fastchat/data/__init__.py
fastchat/data/alpaca-converter.py
fastchat/data/clean_sharegpt.py
fastchat/data/hardcoded_questions.py
fastchat/data/inspect.py
fastchat/data/merge.py
fastchat/data/optional_clean.py
fastchat/data/pretty_json.py
fastchat/data/sample.py
fastchat/data/split_long_conversation.py
fastchat/eval/README.md
fastchat/eval/eval_gpt_review.py
fastchat/eval/generate_webpage_data_from_table.py
fastchat/eval/get_model_answer.py
fastchat/eval/qa_baseline_gpt35.py
fastchat/eval/requirements.txt
fastchat/eval/script/run_model_qa.yaml
fastchat/eval/table/model.jsonl
fastchat/eval/table/prompt.jsonl
fastchat/eval/table/question.jsonl
fastchat/eval/table/reviewer.jsonl
fastchat/eval/table/answer/answer_alpaca-13b.jsonl
fastchat/eval/table/answer/answer_bard.jsonl
fastchat/eval/table/answer/answer_gpt35.jsonl
fastchat/eval/table/answer/answer_llama-13b.jsonl
fastchat/eval/table/answer/answer_vicuna-13b-20230322-new-hp-fp16.jsonl
fastchat/eval/table/answer/answer_vicuna-13b.jsonl
fastchat/eval/table/answer/answer_vicuna-7b-20230322-fp16.jsonl
fastchat/eval/table/review/others/review_llama_alpaca-13b.jsonl
fastchat/eval/table/review/vicuna-13b_20230322-clean-lang/review_alpaca-13b_vicuna-13b.jsonl
fastchat/eval/table/review/vicuna-13b_20230322-clean-lang/review_bard_vicuna-13b.jsonl
fastchat/eval/table/review/vicuna-13b_20230322-clean-lang/review_gpt35_vicuna-13b.jsonl
fastchat/eval/table/review/vicuna-13b_20230322-clean-lang/review_llama-13b_vicuna-13b.jsonl
fastchat/eval/table/review/vicuna-13b_20230322-new-hp-fp16/review_alpaca-13b_vicuna-13b-20230322-new-hp-fp16.jsonl
ytchat-0.0.16.dist-info/LICENSE
ytchat-0.0.16.dist-info/METADATA
ytchat-0.0.16.dist-info/WHEEL
ytchat-0.0.16.dist-info/top_level.txt
ytchat-0.0.16.dist-info/RECORD
