Metadata-Version: 2.1
Name: ytchat
Version: 0.0.16
Summary: An open platform for training, serving, and evaluating large language model based chatbots.
Project-URL: Homepage, https://github.com/yantao0527/fastchat
Project-URL: Bug Tracker, https://github.com/yantao0527/fastchat/issues
Classifier: Programming Language :: Python :: 3
Classifier: License :: OSI Approved :: Apache Software License
Requires-Python: >=3.8
License-File: LICENSE
Requires-Dist: accelerate
Requires-Dist: fastapi
Requires-Dist: gradio (==3.23)
Requires-Dist: markdown2[all]
Requires-Dist: numpy
Requires-Dist: prompt-toolkit (>=3.0.0)
Requires-Dist: requests
Requires-Dist: rich (>=10.0.0)
Requires-Dist: sentencepiece
Requires-Dist: shortuuid
Requires-Dist: transformers (<4.29.0,>=4.28.0)
Requires-Dist: tokenizers (>=0.12.1)
Requires-Dist: torch
Requires-Dist: uvicorn
Requires-Dist: wandb
Requires-Dist: httpx
Requires-Dist: pydantic
Requires-Dist: nh3
Provides-Extra: dev
Requires-Dist: black (==23.3.0) ; extra == 'dev'
Requires-Dist: pylint (==2.8.2) ; extra == 'dev'
